rflx/__init__.py
rflx/__main__.py
rflx/ada.py
rflx/ada_parser.py
rflx/ada_prefix.py
rflx/cli.py
rflx/common.py
rflx/const.py
rflx/converter/__init__.py
rflx/converter/iana.py
rflx/doc/language_reference/_sources/index.rst.txt
rflx/doc/language_reference/_sources/language_reference.rst.txt
rflx/doc/language_reference/_static/adacore-logo-white.png
rflx/doc/language_reference/_static/basic.css
rflx/doc/language_reference/_static/css/badge_only.css
rflx/doc/language_reference/_static/css/custom.css
rflx/doc/language_reference/_static/css/fonts/Roboto-Slab-Bold.woff
rflx/doc/language_reference/_static/css/fonts/Roboto-Slab-Bold.woff2
rflx/doc/language_reference/_static/css/fonts/Roboto-Slab-Regular.woff
rflx/doc/language_reference/_static/css/fonts/Roboto-Slab-Regular.woff2
rflx/doc/language_reference/_static/css/fonts/fontawesome-webfont.eot
rflx/doc/language_reference/_static/css/fonts/fontawesome-webfont.svg
rflx/doc/language_reference/_static/css/fonts/fontawesome-webfont.ttf
rflx/doc/language_reference/_static/css/fonts/fontawesome-webfont.woff
rflx/doc/language_reference/_static/css/fonts/fontawesome-webfont.woff2
rflx/doc/language_reference/_static/css/fonts/lato-bold-italic.woff
rflx/doc/language_reference/_static/css/fonts/lato-bold-italic.woff2
rflx/doc/language_reference/_static/css/fonts/lato-bold.woff
rflx/doc/language_reference/_static/css/fonts/lato-bold.woff2
rflx/doc/language_reference/_static/css/fonts/lato-normal-italic.woff
rflx/doc/language_reference/_static/css/fonts/lato-normal-italic.woff2
rflx/doc/language_reference/_static/css/fonts/lato-normal.woff
rflx/doc/language_reference/_static/css/fonts/lato-normal.woff2
rflx/doc/language_reference/_static/css/theme.css
rflx/doc/language_reference/_static/doctools.js
rflx/doc/language_reference/_static/documentation_options.js
rflx/doc/language_reference/_static/favicon.ico
rflx/doc/language_reference/_static/file.png
rflx/doc/language_reference/_static/jquery-3.5.1.js
recordflux-0.26.0.dist-info/LICENSE
recordflux-0.26.0.dist-info/METADATA
recordflux-0.26.0.dist-info/WHEEL
recordflux-0.26.0.dist-info/entry_points.txt
recordflux-0.26.0.dist-info/RECORD
