Metadata-Version: 2.1
Name: RecordFlux
Version: 0.26.0
Summary: A toolset for the formal specification and generation of verifiable binary parsers, message generators and protocol state machines.
Home-page: https://www.adacore.com/recordflux
License: Apache-2.0
Author: Tobias Reiher
Author-email: reiher@adacore.com
Requires-Python: >=3.9,<4
Classifier: Development Status :: 5 - Production/Stable
Classifier: Environment :: Console
Classifier: License :: OSI Approved :: Apache Software License
Classifier: License :: OSI Approved :: GNU Affero General Public License v3
Classifier: Operating System :: POSIX :: Linux
Classifier: Programming Language :: Ada
Classifier: Programming Language :: Python :: 3
Classifier: Programming Language :: Python :: 3.9
Classifier: Programming Language :: Python :: 3.10
Classifier: Programming Language :: Python :: 3.11
Classifier: Programming Language :: Python :: 3.12
Classifier: Programming Language :: Python :: 3 :: Only
Classifier: Programming Language :: Python :: Implementation :: CPython
Classifier: Programming Language :: Rust
Classifier: Topic :: Communications
Classifier: Topic :: Security
Classifier: Topic :: Software Development :: Build Tools
Classifier: Topic :: Software Development :: Code Generators
Classifier: Topic :: System :: Networking
Requires-Dist: attrs (>=22.1,<24)
Requires-Dist: defusedxml (>=0.7,<0.8)
Requires-Dist: lark (>=1.1.8,<2)
Requires-Dist: pydantic (>=2,<3)
Requires-Dist: pydotplus (>=2,<3)
Requires-Dist: pygls (>=1.1,<2)
Requires-Dist: ruamel.yaml (>=0.18,<0.19)
Requires-Dist: setuptools (>=41)
Requires-Dist: z3-solver (>=4,<4.12.3)
Project-URL: Documentation, https://www.adacore.com/documentation#SPARK
Project-URL: Repository, https://github.com/AdaCore/RecordFlux
